setup.py
ap_package.egg-info/PKG-INFO
ap_package.egg-info/SOURCES.txt
ap_package.egg-info/dependency_links.txt
ap_package.egg-info/top_level.txt
lib/AudioPrecision.API.dll
lib/AudioPrecision.API2.dll
new_ap/__init__.py
new_ap/ap_enum.py
new_ap/apx500.py
new_ap/decorators.py
new_ap/generator.py
new_ap/input_config.py
new_ap/input_connectors.py
new_ap/input_switcher.py
new_ap/output_connectors.py
new_ap/query.py
new_ap/references.py
new_ap/signal_path_setup.py
new_ap/measurement/__init__.py
new_ap/measurement/acoustic_response.py
new_ap/measurement/continuous_sweep.py
new_ap/measurement/fft.py
new_ap/measurement/meters.py
new_ap/measurement/recorder.py
new_ap/measurement/sweep.py
new_ap/measurement/transfer_function.py