Metadata-Version: 2.1
Name: ap-package
Version: 1.0.0
Summary: A description of your library
Author: hatcher
Author-email: your@email.com
